epiaster/__init__.py
epiaster/ensemble.py
epiaster/estimators.py
epiaster/utils.py
epiaster-0.0.2.dist-info/LICENSE
epiaster-0.0.2.dist-info/METADATA
epiaster-0.0.2.dist-info/WHEEL
epiaster-0.0.2.dist-info/top_level.txt
epiaster-0.0.2.dist-info/RECORD
